azureml/__init__.py
azureml/contrib/__init__.py
azureml/contrib/tensorboard/__init__.py
azureml/contrib/tensorboard/export.py
azureml/contrib/tensorboard/tensorboard.py
azureml_contrib_tensorboard-1.0.17.dist-info/DESCRIPTION.rst
azureml_contrib_tensorboard-1.0.17.dist-info/LICENSE.txt
azureml_contrib_tensorboard-1.0.17.dist-info/METADATA
azureml_contrib_tensorboard-1.0.17.dist-info/RECORD
azureml_contrib_tensorboard-1.0.17.dist-info/WHEEL
azureml_contrib_tensorboard-1.0.17.dist-info/metadata.json
azureml_contrib_tensorboard-1.0.17.dist-info/top_level.txt
