Metadata-Version: 2.0
Name: azureml-contrib-tensorboard
Version: 1.0.17
Summary: UNKNOWN
Home-page: https://docs.microsoft.com/en-us/azure/machine-learning/service/
Author: Microsoft Corp
License: Proprietary https://aka.ms/azureml-preview-sdk-license 
Platform: UNKNOWN
Classifier: Development Status :: 3 - Alpha
Classifier: Intended Audience :: Developers
Classifier: Intended Audience :: Science/Research
Classifier: License :: Other/Proprietary License
Classifier: Programming Language :: Python :: 3
Classifier: Programming Language :: Python :: 3.5
Classifier: Programming Language :: Python :: 3.6
Classifier: Topic :: Scientific/Engineering :: Artificial Intelligence
Classifier: Topic :: Multimedia :: Graphics
Classifier: Operating System :: Microsoft :: Windows
Classifier: Operating System :: MacOS
Classifier: Operating System :: POSIX :: Linux
Requires-Dist: azureml-core (==1.0.17.*)
